Metadata-Version: 2.1
Name: gpas-testing
Version: 1.0.1
Summary: Predicting the effect of an antibiotic from gene mutations
Home-page: https://github.com/GlobalPathogenAnalysisService/gpas-testing
Author: Philip W Fowler
Author-email: philip.fowler@ndm.ox.ac.uk
License: MIT
Classifier: Intended Audience :: Science/Research
Classifier: Programming Language :: Python :: 3
Classifier: License :: OSI Approved :: MIT License
Classifier: Operating System :: OS Independent
Requires-Python: >=3.6
License-File: LICENSE
Requires-Dist: pyfastaq (>=3.17.0)
Requires-Dist: pyyaml
Requires-Dist: numpy
Requires-Dist: tqdm
Requires-Dist: pandas
Requires-Dist: gumpy (>=1.0.2)
Requires-Dist: requests
Requires-Dist: pytest
Requires-Dist: pytest-cov
